README.md
setup.py
postman_to_csv/__init__.py
postman_to_csv/__main__.py
postman_to_csv/postman_to_csv.py
postman_to_csv/version.py
postman_to_csv.egg-info/PKG-INFO
postman_to_csv.egg-info/SOURCES.txt
postman_to_csv.egg-info/dependency_links.txt
postman_to_csv.egg-info/entry_points.txt
postman_to_csv.egg-info/top_level.txt