Metadata-Version: 1.1
Name: postman-to-csv
Version: 0.1.0
Summary: A CLI which consumes the JSON output from a Postman test run and outputs a simple CSV format.
Home-page: https://github.com/billtrust/postman-to-csv
Author: Michael Koslap
Author-email: michael.koslap@gmail.com
License: MIT
Keywords: postman,newman
Platform: UNKNOWN
Classifier: Intended Audience :: Developers
Classifier: Natural Language :: English
Classifier: License :: OSI Approved :: MIT License
Classifier: Programming Language :: Python
Classifier: Programming Language :: Python :: 3.6
Classifier: Programming Language :: Python :: 3.7
